onestepx/__init__.py
onestepx/cli.py
onestepx/core.py
onestepx/expr.py
onestepx/hierarchy.py
onestepx/ordinals.py
onestepx/runtime.py
onestepx/temporal.py
onestepx-0.3.7.dist-info/licenses/LICENSE
onestepx_tools/__init__.py
onestepx_tools/cache.py
onestepx-0.3.7.dist-info/METADATA
onestepx-0.3.7.dist-info/WHEEL
onestepx-0.3.7.dist-info/top_level.txt
onestepx-0.3.7.dist-info/RECORD
