Metadata-Version: 2.4
Name: onestepx
Version: 0.3.7
Summary: Instant hierarchical collapse to terminal node (O(1) traversal)
Home-page: https://github.com/mauludsadiq/onestep
Author: Maulud Sadiq
Author-email: mauludsadiq@gmail.com
License: MIT
Classifier: Programming Language :: Python :: 3
Classifier: License :: OSI Approved :: MIT License
Classifier: Operating System :: OS Independent
Requires-Python: >=3.8
License-File: LICENSE
Dynamic: author
Dynamic: author-email
Dynamic: classifier
Dynamic: description
Dynamic: description-content-type
Dynamic: home-page
Dynamic: license
Dynamic: license-file
Dynamic: requires-python
Dynamic: summary
